{"baseBpm":300,"musics":[{"bpm":300,"baseBeats":1,"scores":["d2[J],e2[K],f2[J];d2[K],c2[J];a1[K],f1[J],d2[K];c2[J],f1[K],a1[J];g1[K],f1[J];f1[K],f2[K],T,f1[K];a1[J],a1[K],a1[K];g1[K],a1[K],#a1[J];#a1[K],d2[J],d2[K];c2[K],c2[K],c2[K],#a1[J];g1[K],f1[K],T;T,f2[K],T,f1[K];a1[J],a1[K],a1[K];g1[K],a1[K],#a1[K],T;T,a1[J],a1[K];g1[J],g1[K],g1[K];f1[K],g1[K],a1[K],T;T,f1[J],f1[K];a1[J],a1[K],a1[K];g1[K],a1[K],#a1[K],T;T,d2[J],d2[K];c2[K],c2[K],c2[K],#a1[J];g1[K],f1[K],T;T,f2[J],a1[K];c2[K],c2[K],c2[K],d2[J];d2[K],c2[K],c1[K];f1[K],a1[K],f1[K],a1[K];c2[K],c2[K],c2[K],d2[J];f2[K],","#a[K],d1[K],f1[K],#a[K];d1[K],f1[K],f[K],a[K];c1[K],f[K],a[K],c1[K];c[K],a[K],c1[K],c[K];g[K],#a[K],a[K],f[K];c[K],F-1[K],f[J];f[K],a[K],c1[K],f[K];a[K],c1[K],#a[K],d1[K];f1[K],#a[K],d1[K],f1[K];c[K],a[K],c1[K],c[K];g[K],#a[K],a[K],f[K];c[K],F-1[K],f[J];f[K],a[K],c1[K],f[K];a[K],c1[K],#A-1[K],f[K];#a[K],f[K],a[K],c1[K];c[K],g[K],c1[K],c[K];d[K],e[K],f[K],a[K];c1[K],a[K],f[K],c[K];f[K],a[K],c1[K],f[K];a[K],c1[K],#a[K],d1[K];f1[K],#a[K],d1[K],f1[K];c[K],a[K],c1[K],c[K];d[K],e[K],f[K],c[K];A-1[K],F-1[K],f[J];F-1[K],c[K],f[K],#a[K];d1[K],f1[K],c1[K],f[K];a[K],c1[K],a[K],c[K];F-1[K],c[K],f[K],#a[K];d1[K],f1[K],"],"id":1,"instruments":["piano","piano"],"alternatives":["",""]},{"bpm":316,"baseBeats":1,"scores":["c2[K],c1[K],f1[K],c2[K];a1[K],f1[K],a1[J];a1[K],a1[K],g1[K],a1[K];#a1[K],T,T,a1[J];a1[K],g1[J];g1[K],g1[K],f1[K],g1[K];a1[K],T,T,f1[J];f1[K],a1[J];a1[K],a1[K],g1[K],a1[K];#a1[J],c2[K],d2[J];d2[K],c2[K],c2[K];c2[K],#a1[J],g1[K];f1[K],T,T,f2[J];f2[K],5<a2[L],f2[L]>,5<c2[L],f2[L]>;a2[K],c3[K],f2[K],f2[K];#a2[K],5<U,a2[L]>,5<#a2[L],c3[L]>,d3[J];d3[K],5<c3[L],a2[L]>,5<g2[L],f2[L]>;5<c2[L],c3[L]>,#a2[K],a2[K],g2[K];f2[K],5<U,f2[L]>,5<a2[L],c3[L]>,f3[J];f2[K],5<a2[L],f2[L]>,5<c2[L],f2[L]>;a2[K],c3[K],f3[K],a2[K];#a2[K],5<U,d3[L]>,5<c3[L],#a2[L]>,a2[J];c3[K],g2[K],5<U,a2[L]>;5<g2[L],f2[L]>,c3[K],c2[K],e2[K];f2[K],5<U,f2[L]>,5<a2[L],c3[L]>,f3[K];c3[K],f2[K],5<a2[L],g2[L]>,5<f2[L],g2[L]>;5<a2[L],f2[L]>,5<c3[L],a2[L]>,5<g2[L],f2[L]>,5<a2[L],f2[L]>;","c1[K],f[K],a[K],f[K];c[K],A-1[K],f[K],a[K];c1[K],f[K],a[K],c1[K];#A-1[K],f[K],#a[K],f[K];a[K],c1[K],c[K],g[K];c1[K],#a[K],a[K],g[K];a[K],f[K],c1[K],a[K];f[K],c[K],f[K],a[K];c1[K],f[K],a[K],c1[K];#a[K],d1[K],f1[K],#a[K];d1[K],f1[K],c[K],a[K];c1[K],c[K],d[K],e[K];f[K],c[K],A-1[K],F-1[K];f[J],f[K],a[K];c1[K],f[K],a[K],c1[K];#a[K],d1[K],f1[K],#a[K];d1[K],f1[K],c[K],a[K];c1[K],c[K],d[K],e[K];f[K],c[K],A-1[K],F-1[K];f[J],f[K],a[K];c1[K],f[K],a[K],c1[K];#A-1[K],f[K],#a[K],f[K];a[K],c1[K],c[K],g[K];c1[K],c[K],d[K],e[K];f[K],c[K],A-1[K],F-1[K];f[K],c[K],f[K],a[K];c1[K],f[K],a[K],c1[K];"],"id":2,"instruments":["piano","piano"],"alternatives":["",""]},{"bpm":332,"baseBeats":1,"scores":["#a2[K],5<U,a2[L]>,5<#a2[L],c3[L]>,d3[J];d3[K],c3[K],5<U,a2[L]>;5<#a2[L],c3[L]>,d3[K],f3[K],e3[K];f3[K],5<U,g3[L]>,5<f3[L],e3[L]>,f3[J];a2[K],c3[K],c3[K];c3[K],d3[J],5<e3[L],f3[L]>;c3[K],5<U,c2[L]>,5<f2[L],a2[L]>,5<c3[L],a2[L]>;5<g2[L],f2[L]>,c2[K],c3[K],5<U,a2[L]>;5<#a2[L],c3[L]>,5<d3[L],#c3[L]>,5<d3[L],e3[L]>,5<f3[L],g3[L]>;c3[K],a3[K],f3[K],c3[K];a2[K],f2[K],a2[K],5<U,g2[L]>;5<a2[L],#a2[L]>,c3[K],5<U,a2[L]>,5<#a2[L],c3[L]>;d3[J],d3[K],c3[J];c3[K],#a2[J];#a2[K],#a2[K],a2[K],g2[K];f2[K],c2[K],a2[K],f2[J];f2[K],a2[J];a2[K],a2[K],g2[K],a2[K];#a2[K],5<U,a2[L]>,5<#a2[L],c3[L]>,d3[J];d3[K],c3[K],c3[K];c3[K],d3[J],c3[K];f3[J],a3[K],f3[K];g2[K],a2[K],b2[J];b2[K],b2[K],a2[K],b2[K];c3[K],T,T,b2[J];b2[K],a2[J];a2[K],a2[K],g2[K],a2[K];b2[K],g2[K],d2[K],g2[J];g2[K],b2[J];b2[K],b2[K],a2[K],b2[K];c3[J],d3[K],e3[J];e3[K],d3[K],T;T,#f3[K],T,T;g3[K],T,T,ST;","#a[K],d1[K],f1[K],#a[K];d1[K],f1[K],c[K],a[K];c1[K],c[K],d[K],e[K];f[K],c[K],A-1[K],F-1[K];f[J],F-1[K],c[K];f[K],#a[K],d1[K],#a[K];c1[K],f[K],a[K],c1[K];a[K],c[K],F-1[K],c[K];f[K],#a[K],d1[K],f1[K];c1[K],f[K],a[K],f[K];c[K],A-1[K],f[K],a[K];c1[K],f[K],a[K],c1[K];#A-1[K],f[K],#a[K],f[K];a[K],c1[K],c[K],g[K];c1[K],c[K],d[K],e[K];f[K],c[K],A-1[K],F-1[K];c[K],f[K],f[K],a[K];c1[K],f[K],a[K],c1[K];#a[K],d1[K],f1[K],#a[K];d1[K],f1[K],c[K],a[K];c1[K],c[K],g[K],#a[K];a[K],f[K],c[K],F-1[K];d1[K],d[K],g[K],b[K];d1[K],g[K],b[K],d1[K];c[K],g[K],c1[K],g[K];b[K],d1[K],d[K],a[K];d1[K],c1[K],b[K],a[K];b[K],g[K],d1[K],b[K];g[K],d[K],g[K],b[K];d1[K],g[K],b[K],d1[K];c1[K],e1[K],g1[K],c1[K];e1[K],g1[K],d[K],b[K];d1[K],d[K],a[K],c1[K];b[K],g[K],d[K],G-1[JK];"],"id":3,"instruments":["piano","piano"],"alternatives":["",""]}],"audition":{"end":[0,72],"start":[0,36]}}